Metadata-Version: 2.1
Name: fake0408a
Version: 1.0
Summary: UNKNOWN
Home-page: UNKNOWN
License: UNKNOWN
Platform: UNKNOWN
Requires-Dist: wheel
Requires-Dist: fastapi
Requires-Dist: setuptools
Requires-Dist: twine
Requires-Dist: python-multipart
Requires-Dist: uvicorn
